/*     */ package dao;
/*     */ 
/*     */ import entity.Record;
/*     */ import java.util.List;
/*     */ import util.DateUtil;
/*     */ 
/*     */ public class RecordDAO
/*     */ {
/*     */   /* Error */
/*     */   public int getTotal()
/*     */   {
/*     */     // Byte code:
/*     */     //   0: iconst_0
/*     */     //   1: istore_1
/*     */     //   2: aconst_null
/*     */     //   3: astore_2
/*     */     //   4: aconst_null
/*     */     //   5: astore_3
/*     */     //   6: invokestatic 16	util/DBUtil:getConnection	()Ljava/sql/Connection;
/*     */     //   9: astore 4
/*     */     //   11: aload 4
/*     */     //   13: invokeinterface 22 1 0
/*     */     //   18: astore 5
/*     */     //   20: ldc 28
/*     */     //   22: astore 6
/*     */     //   24: aload 5
/*     */     //   26: aload 6
/*     */     //   28: invokeinterface 30 2 0
/*     */     //   33: astore 7
/*     */     //   35: goto +12 -> 47
/*     */     //   38: aload 7
/*     */     //   40: iconst_1
/*     */     //   41: invokeinterface 36 2 0
/*     */     //   46: istore_1
/*     */     //   47: aload 7
/*     */     //   49: invokeinterface 42 1 0
/*     */     //   54: ifne -16 -> 38
/*     */     //   57: getstatic 46	java/lang/System:out	Ljava/io/PrintStream;
/*     */     //   60: new 52	java/lang/StringBuilder
/*     */     //   63: dup
/*     */     //   64: ldc 54
/*     */     //   66: invokespecial 56	java/lang/StringBuilder:<init>	(Ljava/lang/String;)V
/*     */     //   69: iload_1
/*     */     //   70: invokevirtual 59	java/lang/StringBuilder:append	(I)Ljava/lang/StringBuilder;
/*     */     //   73: invokevirtual 63	java/lang/StringBuilder:toString	()Ljava/lang/String;
/*     */     //   76: invokevirtual 67	java/io/PrintStream:println	(Ljava/lang/String;)V
/*     */     //   79: aload 5
/*     */     //   81: ifnull +28 -> 109
/*     */     //   84: aload 5
/*     */     //   86: invokeinterface 72 1 0
/*     */     //   91: goto +18 -> 109
/*     */     //   94: astore_2
/*     */     //   95: aload 5
/*     */     //   97: ifnull +10 -> 107
/*     */     //   100: aload 5
/*     */     //   102: invokeinterface 72 1 0
/*     */     //   107: aload_2
/*     */     //   108: athrow
/*     */     //   109: aload 4
/*     */     //   111: ifnull +74 -> 185
/*     */     //   114: aload 4
/*     */     //   116: invokeinterface 75 1 0
/*     */     //   121: goto +64 -> 185
/*     */     //   124: astore_3
/*     */     //   125: aload_2
/*     */     //   126: ifnonnull +8 -> 134
/*     */     //   129: aload_3
/*     */     //   130: astore_2
/*     */     //   131: goto +13 -> 144
/*     */     //   134: aload_2
/*     */     //   135: aload_3
/*     */     //   136: if_acmpeq +8 -> 144
/*     */     //   139: aload_2
/*     */     //   140: aload_3
/*     */     //   141: invokevirtual 76	java/lang/Throwable:addSuppressed	(Ljava/lang/Throwable;)V
/*     */     //   144: aload 4
/*     */     //   146: ifnull +10 -> 156
/*     */     //   149: aload 4
/*     */     //   151: invokeinterface 75 1 0
/*     */     //   156: aload_2
/*     */     //   157: athrow
/*     */     //   158: astore_3
/*     */     //   159: aload_2
/*     */     //   160: ifnonnull +8 -> 168
/*     */     //   163: aload_3
/*     */     //   164: astore_2
/*     */     //   165: goto +13 -> 178
/*     */     //   168: aload_2
/*     */     //   169: aload_3
/*     */     //   170: if_acmpeq +8 -> 178
/*     */     //   173: aload_2
/*     */     //   174: aload_3
/*     */     //   175: invokevirtual 76	java/lang/Throwable:addSuppressed	(Ljava/lang/Throwable;)V
/*     */     //   178: aload_2
/*     */     //   179: athrow
/*     */     //   180: astore_2
/*     */     //   181: aload_2
/*     */     //   182: invokevirtual 82	java/sql/SQLException:printStackTrace	()V
/*     */     //   185: iload_1
/*     */     //   186: ireturn
/*     */     // Line number table:
/*     */     //   Java source line #20	-> byte code offset #0
/*     */     //   Java source line #21	-> byte code offset #2
/*     */     //   Java source line #23	-> byte code offset #20
/*     */     //   Java source line #25	-> byte code offset #24
/*     */     //   Java source line #26	-> byte code offset #35
/*     */     //   Java source line #27	-> byte code offset #38
/*     */     //   Java source line #26	-> byte code offset #47
/*     */     //   Java source line #30	-> byte code offset #57
/*     */     //   Java source line #32	-> byte code offset #79
/*     */     //   Java source line #34	-> byte code offset #181
/*     */     //   Java source line #36	-> byte code offset #185
/*     */     // Local variable table:
/*     */     //   start	length	slot	name	signature
/*     */     //   0	187	0	this	RecordDAO
/*     */     //   1	185	1	total	int
/*     */     //   3	1	2	localObject1	Object
/*     */     //   94	32	2	localObject2	Object
/*     */     //   130	49	2	localObject3	Object
/*     */     //   180	2	2	e	java.sql.SQLException
/*     */     //   5	1	3	localObject4	Object
/*     */     //   124	17	3	localThrowable1	Throwable
/*     */     //   158	17	3	localThrowable2	Throwable
/*     */     //   9	141	4	c	java.sql.Connection
/*     */     //   18	83	5	s	java.sql.Statement
/*     */     //   22	5	6	sql	String
/*     */     //   33	15	7	rs	java.sql.ResultSet
/*     */     // Exception table:
/*     */     //   from	to	target	type
/*     */     //   20	79	94	finally
/*     */     //   11	109	124	finally
/*     */     //   6	158	158	finally
/*     */     //   2	180	180	java/sql/SQLException
/*     */   }
/*     */   
/*     */   /* Error */
/*     */   public void add(Record record)
/*     */   {
/*     */     // Byte code:
/*     */     //   0: ldc 104
/*     */     //   2: astore_2
/*     */     //   3: aconst_null
/*     */     //   4: astore_3
/*     */     //   5: aconst_null
/*     */     //   6: astore 4
/*     */     //   8: invokestatic 16	util/DBUtil:getConnection	()Ljava/sql/Connection;
/*     */     //   11: astore 5
/*     */     //   13: aload 5
/*     */     //   15: aload_2
/*     */     //   16: invokeinterface 106 2 0
/*     */     //   21: astore 6
/*     */     //   23: aload 6
/*     */     //   25: iconst_1
/*     */     //   26: aload_1
/*     */     //   27: getfield 110	entity/Record:spend	I
/*     */     //   30: invokeinterface 115 3 0
/*     */     //   35: aload 6
/*     */     //   37: iconst_2
/*     */     //   38: aload_1
/*     */     //   39: getfield 121	entity/Record:cid	I
/*     */     //   42: invokeinterface 115 3 0
/*     */     //   47: aload 6
/*     */     //   49: iconst_3
/*     */     //   50: aload_1
/*     */     //   51: getfield 124	entity/Record:comment	Ljava/lang/String;
/*     */     //   54: invokeinterface 127 3 0
/*     */     //   59: aload 6
/*     */     //   61: iconst_4
/*     */     //   62: aload_1
/*     */     //   63: getfield 131	entity/Record:date	Ljava/util/Date;
/*     */     //   66: invokestatic 135	util/DateUtil:util2sql	(Ljava/util/Date;)Ljava/sql/Date;
/*     */     //   69: invokeinterface 141 3 0
/*     */     //   74: aload 6
/*     */     //   76: invokeinterface 145 1 0
/*     */     //   81: pop
/*     */     //   82: aload 6
/*     */     //   84: invokeinterface 148 1 0
/*     */     //   89: astore 7
/*     */     //   91: aload 7
/*     */     //   93: invokeinterface 42 1 0
/*     */     //   98: ifeq +19 -> 117
/*     */     //   101: aload 7
/*     */     //   103: iconst_1
/*     */     //   104: invokeinterface 36 2 0
/*     */     //   109: istore 8
/*     */     //   111: aload_1
/*     */     //   112: iload 8
/*     */     //   114: putfield 152	entity/Record:id	I
/*     */     //   117: aload 6
/*     */     //   119: ifnull +28 -> 147
/*     */     //   122: aload 6
/*     */     //   124: invokeinterface 155 1 0
/*     */     //   129: goto +18 -> 147
/*     */     //   132: astore_3
/*     */     //   133: aload 6
/*     */     //   135: ifnull +10 -> 145
/*     */     //   138: aload 6
/*     */     //   140: invokeinterface 155 1 0
/*     */     //   145: aload_3
/*     */     //   146: athrow
/*     */     //   147: aload 5
/*     */     //   149: ifnull +82 -> 231
/*     */     //   152: aload 5
/*     */     //   154: invokeinterface 75 1 0
/*     */     //   159: goto +72 -> 231
/*     */     //   162: astore 4
/*     */     //   164: aload_3
/*     */     //   165: ifnonnull +9 -> 174
/*     */     //   168: aload 4
/*     */     //   170: astore_3
/*     */     //   171: goto +15 -> 186
/*     */     //   174: aload_3
/*     */     //   175: aload 4
/*     */     //   177: if_acmpeq +9 -> 186
/*     */     //   180: aload_3
/*     */     //   181: aload 4
/*     */     //   183: invokevirtual 76	java/lang/Throwable:addSuppressed	(Ljava/lang/Throwable;)V
/*     */     //   186: aload 5
/*     */     //   188: ifnull +10 -> 198
/*     */     //   191: aload 5
/*     */     //   193: invokeinterface 75 1 0
/*     */     //   198: aload_3
/*     */     //   199: athrow
/*     */     //   200: astore 4
/*     */     //   202: aload_3
/*     */     //   203: ifnonnull +9 -> 212
/*     */     //   206: aload 4
/*     */     //   208: astore_3
/*     */     //   209: goto +15 -> 224
/*     */     //   212: aload_3
/*     */     //   213: aload 4
/*     */     //   215: if_acmpeq +9 -> 224
/*     */     //   218: aload_3
/*     */     //   219: aload 4
/*     */     //   221: invokevirtual 76	java/lang/Throwable:addSuppressed	(Ljava/lang/Throwable;)V
/*     */     //   224: aload_3
/*     */     //   225: athrow
/*     */     //   226: astore_3
/*     */     //   227: aload_3
/*     */     //   228: invokevirtual 82	java/sql/SQLException:printStackTrace	()V
/*     */     //   231: return
/*     */     // Line number table:
/*     */     //   Java source line #41	-> byte code offset #0
/*     */     //   Java source line #42	-> byte code offset #3
/*     */     //   Java source line #42	-> byte code offset #8
/*     */     //   Java source line #43	-> byte code offset #23
/*     */     //   Java source line #44	-> byte code offset #35
/*     */     //   Java source line #45	-> byte code offset #47
/*     */     //   Java source line #46	-> byte code offset #59
/*     */     //   Java source line #48	-> byte code offset #74
/*     */     //   Java source line #50	-> byte code offset #82
/*     */     //   Java source line #51	-> byte code offset #91
/*     */     //   Java source line #52	-> byte code offset #101
/*     */     //   Java source line #53	-> byte code offset #111
/*     */     //   Java source line #55	-> byte code offset #117
/*     */     //   Java source line #57	-> byte code offset #227
/*     */     //   Java source line #59	-> byte code offset #231
/*     */     // Local variable table:
/*     */     //   start	length	slot	name	signature
/*     */     //   0	232	0	this	RecordDAO
/*     */     //   0	232	1	record	Record
/*     */     //   2	14	2	sql	String
/*     */     //   4	1	3	localObject1	Object
/*     */     //   132	33	3	localObject2	Object
/*     */     //   170	55	3	localObject3	Object
/*     */     //   226	2	3	e	java.sql.SQLException
/*     */     //   6	1	4	localObject4	Object
/*     */     //   162	20	4	localThrowable1	Throwable
/*     */     //   200	20	4	localThrowable2	Throwable
/*     */     //   11	181	5	c	java.sql.Connection
/*     */     //   21	118	6	ps	java.sql.PreparedStatement
/*     */     //   89	13	7	rs	java.sql.ResultSet
/*     */     //   109	4	8	id	int
/*     */     // Exception table:
/*     */     //   from	to	target	type
/*     */     //   23	117	132	finally
/*     */     //   13	147	162	finally
/*     */     //   8	200	200	finally
/*     */     //   3	226	226	java/sql/SQLException
/*     */   }
/*     */   
/*     */   /* Error */
/*     */   public void update(Record record)
/*     */   {
/*     */     // Byte code:
/*     */     //   0: ldc -95
/*     */     //   2: astore_2
/*     */     //   3: aconst_null
/*     */     //   4: astore_3
/*     */     //   5: aconst_null
/*     */     //   6: astore 4
/*     */     //   8: invokestatic 16	util/DBUtil:getConnection	()Ljava/sql/Connection;
/*     */     //   11: astore 5
/*     */     //   13: aload 5
/*     */     //   15: aload_2
/*     */     //   16: invokeinterface 106 2 0
/*     */     //   21: astore 6
/*     */     //   23: aload 6
/*     */     //   25: iconst_1
/*     */     //   26: aload_1
/*     */     //   27: getfield 110	entity/Record:spend	I
/*     */     //   30: invokeinterface 115 3 0
/*     */     //   35: aload 6
/*     */     //   37: iconst_2
/*     */     //   38: aload_1
/*     */     //   39: getfield 121	entity/Record:cid	I
/*     */     //   42: invokeinterface 115 3 0
/*     */     //   47: aload 6
/*     */     //   49: iconst_3
/*     */     //   50: aload_1
/*     */     //   51: getfield 124	entity/Record:comment	Ljava/lang/String;
/*     */     //   54: invokeinterface 127 3 0
/*     */     //   59: aload 6
/*     */     //   61: iconst_4
/*     */     //   62: aload_1
/*     */     //   63: getfield 131	entity/Record:date	Ljava/util/Date;
/*     */     //   66: invokestatic 135	util/DateUtil:util2sql	(Ljava/util/Date;)Ljava/sql/Date;
/*     */     //   69: invokeinterface 141 3 0
/*     */     //   74: aload 6
/*     */     //   76: iconst_5
/*     */     //   77: aload_1
/*     */     //   78: getfield 152	entity/Record:id	I
/*     */     //   81: invokeinterface 115 3 0
/*     */     //   86: aload 6
/*     */     //   88: invokeinterface 145 1 0
/*     */     //   93: pop
/*     */     //   94: aload 6
/*     */     //   96: ifnull +28 -> 124
/*     */     //   99: aload 6
/*     */     //   101: invokeinterface 155 1 0
/*     */     //   106: goto +18 -> 124
/*     */     //   109: astore_3
/*     */     //   110: aload 6
/*     */     //   112: ifnull +10 -> 122
/*     */     //   115: aload 6
/*     */     //   117: invokeinterface 155 1 0
/*     */     //   122: aload_3
/*     */     //   123: athrow
/*     */     //   124: aload 5
/*     */     //   126: ifnull +82 -> 208
/*     */     //   129: aload 5
/*     */     //   131: invokeinterface 75 1 0
/*     */     //   136: goto +72 -> 208
/*     */     //   139: astore 4
/*     */     //   141: aload_3
/*     */     //   142: ifnonnull +9 -> 151
/*     */     //   145: aload 4
/*     */     //   147: astore_3
/*     */     //   148: goto +15 -> 163
/*     */     //   151: aload_3
/*     */     //   152: aload 4
/*     */     //   154: if_acmpeq +9 -> 163
/*     */     //   157: aload_3
/*     */     //   158: aload 4
/*     */     //   160: invokevirtual 76	java/lang/Throwable:addSuppressed	(Ljava/lang/Throwable;)V
/*     */     //   163: aload 5
/*     */     //   165: ifnull +10 -> 175
/*     */     //   168: aload 5
/*     */     //   170: invokeinterface 75 1 0
/*     */     //   175: aload_3
/*     */     //   176: athrow
/*     */     //   177: astore 4
/*     */     //   179: aload_3
/*     */     //   180: ifnonnull +9 -> 189
/*     */     //   183: aload 4
/*     */     //   185: astore_3
/*     */     //   186: goto +15 -> 201
/*     */     //   189: aload_3
/*     */     //   190: aload 4
/*     */     //   192: if_acmpeq +9 -> 201
/*     */     //   195: aload_3
/*     */     //   196: aload 4
/*     */     //   198: invokevirtual 76	java/lang/Throwable:addSuppressed	(Ljava/lang/Throwable;)V
/*     */     //   201: aload_3
/*     */     //   202: athrow
/*     */     //   203: astore_3
/*     */     //   204: aload_3
/*     */     //   205: invokevirtual 82	java/sql/SQLException:printStackTrace	()V
/*     */     //   208: return
/*     */     // Line number table:
/*     */     //   Java source line #63	-> byte code offset #0
/*     */     //   Java source line #64	-> byte code offset #3
/*     */     //   Java source line #64	-> byte code offset #8
/*     */     //   Java source line #66	-> byte code offset #23
/*     */     //   Java source line #67	-> byte code offset #35
/*     */     //   Java source line #68	-> byte code offset #47
/*     */     //   Java source line #69	-> byte code offset #59
/*     */     //   Java source line #70	-> byte code offset #74
/*     */     //   Java source line #72	-> byte code offset #86
/*     */     //   Java source line #74	-> byte code offset #94
/*     */     //   Java source line #76	-> byte code offset #204
/*     */     //   Java source line #79	-> byte code offset #208
/*     */     // Local variable table:
/*     */     //   start	length	slot	name	signature
/*     */     //   0	209	0	this	RecordDAO
/*     */     //   0	209	1	record	Record
/*     */     //   2	14	2	sql	String
/*     */     //   4	1	3	localObject1	Object
/*     */     //   109	33	3	localObject2	Object
/*     */     //   147	55	3	localObject3	Object
/*     */     //   203	2	3	e	java.sql.SQLException
/*     */     //   6	1	4	localObject4	Object
/*     */     //   139	20	4	localThrowable1	Throwable
/*     */     //   177	20	4	localThrowable2	Throwable
/*     */     //   11	158	5	c	java.sql.Connection
/*     */     //   21	95	6	ps	java.sql.PreparedStatement
/*     */     // Exception table:
/*     */     //   from	to	target	type
/*     */     //   23	94	109	finally
/*     */     //   13	124	139	finally
/*     */     //   8	177	177	finally
/*     */     //   3	203	203	java/sql/SQLException
/*     */   }
/*     */   
/*     */   /* Error */
/*     */   public void delete(int id)
/*     */   {
/*     */     // Byte code:
/*     */     //   0: aconst_null
/*     */     //   1: astore_2
/*     */     //   2: aconst_null
/*     */     //   3: astore_3
/*     */     //   4: invokestatic 16	util/DBUtil:getConnection	()Ljava/sql/Connection;
/*     */     //   7: astore 4
/*     */     //   9: aload 4
/*     */     //   11: invokeinterface 22 1 0
/*     */     //   16: astore 5
/*     */     //   18: new 52	java/lang/StringBuilder
/*     */     //   21: dup
/*     */     //   22: ldc -91
/*     */     //   24: invokespecial 56	java/lang/StringBuilder:<init>	(Ljava/lang/String;)V
/*     */     //   27: iload_1
/*     */     //   28: invokevirtual 59	java/lang/StringBuilder:append	(I)Ljava/lang/StringBuilder;
/*     */     //   31: invokevirtual 63	java/lang/StringBuilder:toString	()Ljava/lang/String;
/*     */     //   34: astore 6
/*     */     //   36: aload 5
/*     */     //   38: aload 6
/*     */     //   40: invokeinterface 167 2 0
/*     */     //   45: pop
/*     */     //   46: aload 5
/*     */     //   48: ifnull +28 -> 76
/*     */     //   51: aload 5
/*     */     //   53: invokeinterface 72 1 0
/*     */     //   58: goto +18 -> 76
/*     */     //   61: astore_2
/*     */     //   62: aload 5
/*     */     //   64: ifnull +10 -> 74
/*     */     //   67: aload 5
/*     */     //   69: invokeinterface 72 1 0
/*     */     //   74: aload_2
/*     */     //   75: athrow
/*     */     //   76: aload 4
/*     */     //   78: ifnull +74 -> 152
/*     */     //   81: aload 4
/*     */     //   83: invokeinterface 75 1 0
/*     */     //   88: goto +64 -> 152
/*     */     //   91: astore_3
/*     */     //   92: aload_2
/*     */     //   93: ifnonnull +8 -> 101
/*     */     //   96: aload_3
/*     */     //   97: astore_2
/*     */     //   98: goto +13 -> 111
/*     */     //   101: aload_2
/*     */     //   102: aload_3
/*     */     //   103: if_acmpeq +8 -> 111
/*     */     //   106: aload_2
/*     */     //   107: aload_3
/*     */     //   108: invokevirtual 76	java/lang/Throwable:addSuppressed	(Ljava/lang/Throwable;)V
/*     */     //   111: aload 4
/*     */     //   113: ifnull +10 -> 123
/*     */     //   116: aload 4
/*     */     //   118: invokeinterface 75 1 0
/*     */     //   123: aload_2
/*     */     //   124: athrow
/*     */     //   125: astore_3
/*     */     //   126: aload_2
/*     */     //   127: ifnonnull +8 -> 135
/*     */     //   130: aload_3
/*     */     //   131: astore_2
/*     */     //   132: goto +13 -> 145
/*     */     //   135: aload_2
/*     */     //   136: aload_3
/*     */     //   137: if_acmpeq +8 -> 145
/*     */     //   140: aload_2
/*     */     //   141: aload_3
/*     */     //   142: invokevirtual 76	java/lang/Throwable:addSuppressed	(Ljava/lang/Throwable;)V
/*     */     //   145: aload_2
/*     */     //   146: athrow
/*     */     //   147: astore_2
/*     */     //   148: aload_2
/*     */     //   149: invokevirtual 82	java/sql/SQLException:printStackTrace	()V
/*     */     //   152: return
/*     */     // Line number table:
/*     */     //   Java source line #83	-> byte code offset #0
/*     */     //   Java source line #85	-> byte code offset #18
/*     */     //   Java source line #87	-> byte code offset #36
/*     */     //   Java source line #89	-> byte code offset #46
/*     */     //   Java source line #91	-> byte code offset #148
/*     */     //   Java source line #93	-> byte code offset #152
/*     */     // Local variable table:
/*     */     //   start	length	slot	name	signature
/*     */     //   0	153	0	this	RecordDAO
/*     */     //   0	153	1	id	int
/*     */     //   1	1	2	localObject1	Object
/*     */     //   61	32	2	localObject2	Object
/*     */     //   97	49	2	localObject3	Object
/*     */     //   147	2	2	e	java.sql.SQLException
/*     */     //   3	1	3	localObject4	Object
/*     */     //   91	17	3	localThrowable1	Throwable
/*     */     //   125	17	3	localThrowable2	Throwable
/*     */     //   7	110	4	c	java.sql.Connection
/*     */     //   16	52	5	s	java.sql.Statement
/*     */     //   34	5	6	sql	String
/*     */     // Exception table:
/*     */     //   from	to	target	type
/*     */     //   18	46	61	finally
/*     */     //   9	76	91	finally
/*     */     //   4	125	125	finally
/*     */     //   0	147	147	java/sql/SQLException
/*     */   }
/*     */   
/*     */   /* Error */
/*     */   public Record get(int id)
/*     */   {
/*     */     // Byte code:
/*     */     //   0: aconst_null
/*     */     //   1: astore_2
/*     */     //   2: aconst_null
/*     */     //   3: astore_3
/*     */     //   4: aconst_null
/*     */     //   5: astore 4
/*     */     //   7: invokestatic 16	util/DBUtil:getConnection	()Ljava/sql/Connection;
/*     */     //   10: astore 5
/*     */     //   12: aload 5
/*     */     //   14: invokeinterface 22 1 0
/*     */     //   19: astore 6
/*     */     //   21: new 52	java/lang/StringBuilder
/*     */     //   24: dup
/*     */     //   25: ldc -84
/*     */     //   27: invokespecial 56	java/lang/StringBuilder:<init>	(Ljava/lang/String;)V
/*     */     //   30: iload_1
/*     */     //   31: invokevirtual 59	java/lang/StringBuilder:append	(I)Ljava/lang/StringBuilder;
/*     */     //   34: invokevirtual 63	java/lang/StringBuilder:toString	()Ljava/lang/String;
/*     */     //   37: astore 7
/*     */     //   39: aload 6
/*     */     //   41: aload 7
/*     */     //   43: invokeinterface 30 2 0
/*     */     //   48: astore 8
/*     */     //   50: aload 8
/*     */     //   52: invokeinterface 42 1 0
/*     */     //   57: ifeq +84 -> 141
/*     */     //   60: new 111	entity/Record
/*     */     //   63: dup
/*     */     //   64: invokespecial 174	entity/Record:<init>	()V
/*     */     //   67: astore_2
/*     */     //   68: aload 8
/*     */     //   70: ldc -81
/*     */     //   72: invokeinterface 176 2 0
/*     */     //   77: istore 9
/*     */     //   79: aload 8
/*     */     //   81: ldc -77
/*     */     //   83: invokeinterface 176 2 0
/*     */     //   88: istore 10
/*     */     //   90: aload 8
/*     */     //   92: ldc -76
/*     */     //   94: invokeinterface 181 2 0
/*     */     //   99: astore 11
/*     */     //   101: aload 8
/*     */     //   103: ldc -71
/*     */     //   105: invokeinterface 186 2 0
/*     */     //   110: astore 12
/*     */     //   112: aload_2
/*     */     //   113: iload 9
/*     */     //   115: putfield 110	entity/Record:spend	I
/*     */     //   118: aload_2
/*     */     //   119: iload 10
/*     */     //   121: putfield 121	entity/Record:cid	I
/*     */     //   124: aload_2
/*     */     //   125: aload 11
/*     */     //   127: putfield 124	entity/Record:comment	Ljava/lang/String;
/*     */     //   130: aload_2
/*     */     //   131: aload 12
/*     */     //   133: putfield 131	entity/Record:date	Ljava/util/Date;
/*     */     //   136: aload_2
/*     */     //   137: iload_1
/*     */     //   138: putfield 152	entity/Record:id	I
/*     */     //   141: aload 6
/*     */     //   143: ifnull +28 -> 171
/*     */     //   146: aload 6
/*     */     //   148: invokeinterface 72 1 0
/*     */     //   153: goto +18 -> 171
/*     */     //   156: astore_3
/*     */     //   157: aload 6
/*     */     //   159: ifnull +10 -> 169
/*     */     //   162: aload 6
/*     */     //   164: invokeinterface 72 1 0
/*     */     //   169: aload_3
/*     */     //   170: athrow
/*     */     //   171: aload 5
/*     */     //   173: ifnull +82 -> 255
/*     */     //   176: aload 5
/*     */     //   178: invokeinterface 75 1 0
/*     */     //   183: goto +72 -> 255
/*     */     //   186: astore 4
/*     */     //   188: aload_3
/*     */     //   189: ifnonnull +9 -> 198
/*     */     //   192: aload 4
/*     */     //   194: astore_3
/*     */     //   195: goto +15 -> 210
/*     */     //   198: aload_3
/*     */     //   199: aload 4
/*     */     //   201: if_acmpeq +9 -> 210
/*     */     //   204: aload_3
/*     */     //   205: aload 4
/*     */     //   207: invokevirtual 76	java/lang/Throwable:addSuppressed	(Ljava/lang/Throwable;)V
/*     */     //   210: aload 5
/*     */     //   212: ifnull +10 -> 222
/*     */     //   215: aload 5
/*     */     //   217: invokeinterface 75 1 0
/*     */     //   222: aload_3
/*     */     //   223: athrow
/*     */     //   224: astore 4
/*     */     //   226: aload_3
/*     */     //   227: ifnonnull +9 -> 236
/*     */     //   230: aload 4
/*     */     //   232: astore_3
/*     */     //   233: goto +15 -> 248
/*     */     //   236: aload_3
/*     */     //   237: aload 4
/*     */     //   239: if_acmpeq +9 -> 248
/*     */     //   242: aload_3
/*     */     //   243: aload 4
/*     */     //   245: invokevirtual 76	java/lang/Throwable:addSuppressed	(Ljava/lang/Throwable;)V
/*     */     //   248: aload_3
/*     */     //   249: athrow
/*     */     //   250: astore_3
/*     */     //   251: aload_3
/*     */     //   252: invokevirtual 82	java/sql/SQLException:printStackTrace	()V
/*     */     //   255: aload_2
/*     */     //   256: areturn
/*     */     // Line number table:
/*     */     //   Java source line #96	-> byte code offset #0
/*     */     //   Java source line #98	-> byte code offset #2
/*     */     //   Java source line #100	-> byte code offset #21
/*     */     //   Java source line #102	-> byte code offset #39
/*     */     //   Java source line #104	-> byte code offset #50
/*     */     //   Java source line #105	-> byte code offset #60
/*     */     //   Java source line #106	-> byte code offset #68
/*     */     //   Java source line #107	-> byte code offset #79
/*     */     //   Java source line #108	-> byte code offset #90
/*     */     //   Java source line #109	-> byte code offset #101
/*     */     //   Java source line #111	-> byte code offset #112
/*     */     //   Java source line #112	-> byte code offset #118
/*     */     //   Java source line #113	-> byte code offset #124
/*     */     //   Java source line #114	-> byte code offset #130
/*     */     //   Java source line #115	-> byte code offset #136
/*     */     //   Java source line #118	-> byte code offset #141
/*     */     //   Java source line #120	-> byte code offset #251
/*     */     //   Java source line #122	-> byte code offset #255
/*     */     // Local variable table:
/*     */     //   start	length	slot	name	signature
/*     */     //   0	257	0	this	RecordDAO
/*     */     //   0	257	1	id	int
/*     */     //   1	255	2	record	Record
/*     */     //   3	1	3	localObject1	Object
/*     */     //   156	33	3	localObject2	Object
/*     */     //   194	55	3	localObject3	Object
/*     */     //   250	2	3	e	java.sql.SQLException
/*     */     //   5	1	4	localObject4	Object
/*     */     //   186	20	4	localThrowable1	Throwable
/*     */     //   224	20	4	localThrowable2	Throwable
/*     */     //   10	206	5	c	java.sql.Connection
/*     */     //   19	144	6	s	java.sql.Statement
/*     */     //   37	5	7	sql	String
/*     */     //   48	54	8	rs	java.sql.ResultSet
/*     */     //   77	37	9	spend	int
/*     */     //   88	32	10	cid	int
/*     */     //   99	27	11	comment	String
/*     */     //   110	22	12	date	java.util.Date
/*     */     // Exception table:
/*     */     //   from	to	target	type
/*     */     //   21	141	156	finally
/*     */     //   12	171	186	finally
/*     */     //   7	224	224	finally
/*     */     //   2	250	250	java/sql/SQLException
/*     */   }
/*     */   
/*     */   public List<Record> list()
/*     */   {
/* 126 */     return list(0, 32767);
/*     */   }
/*     */   
/*     */   /* Error */
/*     */   public List<Record> list(int start, int count)
/*     */   {
/*     */     // Byte code:
/*     */     //   0: new 198	java/util/ArrayList
/*     */     //   3: dup
/*     */     //   4: invokespecial 200	java/util/ArrayList:<init>	()V
/*     */     //   7: astore_3
/*     */     //   8: ldc -55
/*     */     //   10: astore 4
/*     */     //   12: aconst_null
/*     */     //   13: astore 5
/*     */     //   15: aconst_null
/*     */     //   16: astore 6
/*     */     //   18: invokestatic 16	util/DBUtil:getConnection	()Ljava/sql/Connection;
/*     */     //   21: astore 7
/*     */     //   23: aload 7
/*     */     //   25: aload 4
/*     */     //   27: invokeinterface 106 2 0
/*     */     //   32: astore 8
/*     */     //   34: aload 8
/*     */     //   36: iconst_1
/*     */     //   37: iload_1
/*     */     //   38: invokeinterface 115 3 0
/*     */     //   43: aload 8
/*     */     //   45: iconst_2
/*     */     //   46: iload_2
/*     */     //   47: invokeinterface 115 3 0
/*     */     //   52: aload 8
/*     */     //   54: invokeinterface 203 1 0
/*     */     //   59: astore 9
/*     */     //   61: goto +111 -> 172
/*     */     //   64: new 111	entity/Record
/*     */     //   67: dup
/*     */     //   68: invokespecial 174	entity/Record:<init>	()V
/*     */     //   71: astore 10
/*     */     //   73: aload 9
/*     */     //   75: ldc -51
/*     */     //   77: invokeinterface 176 2 0
/*     */     //   82: istore 11
/*     */     //   84: aload 9
/*     */     //   86: ldc -81
/*     */     //   88: invokeinterface 176 2 0
/*     */     //   93: istore 12
/*     */     //   95: aload 9
/*     */     //   97: ldc -77
/*     */     //   99: invokeinterface 176 2 0
/*     */     //   104: istore 13
/*     */     //   106: aload 9
/*     */     //   108: ldc -76
/*     */     //   110: invokeinterface 181 2 0
/*     */     //   115: astore 14
/*     */     //   117: aload 9
/*     */     //   119: ldc -71
/*     */     //   121: invokeinterface 186 2 0
/*     */     //   126: astore 15
/*     */     //   128: aload 10
/*     */     //   130: iload 12
/*     */     //   132: putfield 110	entity/Record:spend	I
/*     */     //   135: aload 10
/*     */     //   137: iload 13
/*     */     //   139: putfield 121	entity/Record:cid	I
/*     */     //   142: aload 10
/*     */     //   144: aload 14
/*     */     //   146: putfield 124	entity/Record:comment	Ljava/lang/String;
/*     */     //   149: aload 10
/*     */     //   151: aload 15
/*     */     //   153: putfield 131	entity/Record:date	Ljava/util/Date;
/*     */     //   156: aload 10
/*     */     //   158: iload 11
/*     */     //   160: putfield 152	entity/Record:id	I
/*     */     //   163: aload_3
/*     */     //   164: aload 10
/*     */     //   166: invokeinterface 206 2 0
/*     */     //   171: pop
/*     */     //   172: aload 9
/*     */     //   174: invokeinterface 42 1 0
/*     */     //   179: ifne -115 -> 64
/*     */     //   182: aload 8
/*     */     //   184: ifnull +30 -> 214
/*     */     //   187: aload 8
/*     */     //   189: invokeinterface 155 1 0
/*     */     //   194: goto +20 -> 214
/*     */     //   197: astore 5
/*     */     //   199: aload 8
/*     */     //   201: ifnull +10 -> 211
/*     */     //   204: aload 8
/*     */     //   206: invokeinterface 155 1 0
/*     */     //   211: aload 5
/*     */     //   213: athrow
/*     */     //   214: aload 7
/*     */     //   216: ifnull +94 -> 310
/*     */     //   219: aload 7
/*     */     //   221: invokeinterface 75 1 0
/*     */     //   226: goto +84 -> 310
/*     */     //   229: astore 6
/*     */     //   231: aload 5
/*     */     //   233: ifnonnull +10 -> 243
/*     */     //   236: aload 6
/*     */     //   238: astore 5
/*     */     //   240: goto +17 -> 257
/*     */     //   243: aload 5
/*     */     //   245: aload 6
/*     */     //   247: if_acmpeq +10 -> 257
/*     */     //   250: aload 5
/*     */     //   252: aload 6
/*     */     //   254: invokevirtual 76	java/lang/Throwable:addSuppressed	(Ljava/lang/Throwable;)V
/*     */     //   257: aload 7
/*     */     //   259: ifnull +10 -> 269
/*     */     //   262: aload 7
/*     */     //   264: invokeinterface 75 1 0
/*     */     //   269: aload 5
/*     */     //   271: athrow
/*     */     //   272: astore 6
/*     */     //   274: aload 5
/*     */     //   276: ifnonnull +10 -> 286
/*     */     //   279: aload 6
/*     */     //   281: astore 5
/*     */     //   283: goto +17 -> 300
/*     */     //   286: aload 5
/*     */     //   288: aload 6
/*     */     //   290: if_acmpeq +10 -> 300
/*     */     //   293: aload 5
/*     */     //   295: aload 6
/*     */     //   297: invokevirtual 76	java/lang/Throwable:addSuppressed	(Ljava/lang/Throwable;)V
/*     */     //   300: aload 5
/*     */     //   302: athrow
/*     */     //   303: astore 5
/*     */     //   305: aload 5
/*     */     //   307: invokevirtual 82	java/sql/SQLException:printStackTrace	()V
/*     */     //   310: aload_3
/*     */     //   311: areturn
/*     */     // Line number table:
/*     */     //   Java source line #130	-> byte code offset #0
/*     */     //   Java source line #132	-> byte code offset #8
/*     */     //   Java source line #134	-> byte code offset #12
/*     */     //   Java source line #134	-> byte code offset #18
/*     */     //   Java source line #136	-> byte code offset #34
/*     */     //   Java source line #137	-> byte code offset #43
/*     */     //   Java source line #139	-> byte code offset #52
/*     */     //   Java source line #141	-> byte code offset #61
/*     */     //   Java source line #142	-> byte code offset #64
/*     */     //   Java source line #143	-> byte code offset #73
/*     */     //   Java source line #144	-> byte code offset #84
/*     */     //   Java source line #145	-> byte code offset #95
/*     */     //   Java source line #147	-> byte code offset #106
/*     */     //   Java source line #148	-> byte code offset #117
/*     */     //   Java source line #150	-> byte code offset #128
/*     */     //   Java source line #151	-> byte code offset #135
/*     */     //   Java source line #152	-> byte code offset #142
/*     */     //   Java source line #153	-> byte code offset #149
/*     */     //   Java source line #154	-> byte code offset #156
/*     */     //   Java source line #155	-> byte code offset #163
/*     */     //   Java source line #141	-> byte code offset #172
/*     */     //   Java source line #157	-> byte code offset #182
/*     */     //   Java source line #159	-> byte code offset #305
/*     */     //   Java source line #161	-> byte code offset #310
/*     */     // Local variable table:
/*     */     //   start	length	slot	name	signature
/*     */     //   0	312	0	this	RecordDAO
/*     */     //   0	312	1	start	int
/*     */     //   0	312	2	count	int
/*     */     //   7	304	3	records	List<Record>
/*     */     //   10	16	4	sql	String
/*     */     //   13	1	5	localObject1	Object
/*     */     //   197	35	5	localObject2	Object
/*     */     //   238	63	5	localObject3	Object
/*     */     //   303	3	5	e	java.sql.SQLException
/*     */     //   16	1	6	localObject4	Object
/*     */     //   229	24	6	localThrowable1	Throwable
/*     */     //   272	24	6	localThrowable2	Throwable
/*     */     //   21	242	7	c	java.sql.Connection
/*     */     //   32	173	8	ps	java.sql.PreparedStatement
/*     */     //   59	114	9	rs	java.sql.ResultSet
/*     */     //   71	94	10	record	Record
/*     */     //   82	77	11	id	int
/*     */     //   93	38	12	spend	int
/*     */     //   104	34	13	cid	int
/*     */     //   115	30	14	comment	String
/*     */     //   126	26	15	date	java.util.Date
/*     */     // Exception table:
/*     */     //   from	to	target	type
/*     */     //   34	182	197	finally
/*     */     //   23	214	229	finally
/*     */     //   18	272	272	finally
/*     */     //   12	303	303	java/sql/SQLException
/*     */   }
/*     */   
/*     */   /* Error */
/*     */   public List<Record> list(int cid)
/*     */   {
/*     */     // Byte code:
/*     */     //   0: new 198	java/util/ArrayList
/*     */     //   3: dup
/*     */     //   4: invokespecial 200	java/util/ArrayList:<init>	()V
/*     */     //   7: astore_2
/*     */     //   8: ldc -37
/*     */     //   10: astore_3
/*     */     //   11: aconst_null
/*     */     //   12: astore 4
/*     */     //   14: aconst_null
/*     */     //   15: astore 5
/*     */     //   17: invokestatic 16	util/DBUtil:getConnection	()Ljava/sql/Connection;
/*     */     //   20: astore 6
/*     */     //   22: aload 6
/*     */     //   24: aload_3
/*     */     //   25: invokeinterface 106 2 0
/*     */     //   30: astore 7
/*     */     //   32: aload 7
/*     */     //   34: iconst_1
/*     */     //   35: iload_1
/*     */     //   36: invokeinterface 115 3 0
/*     */     //   41: aload 7
/*     */     //   43: invokeinterface 203 1 0
/*     */     //   48: astore 8
/*     */     //   50: goto +99 -> 149
/*     */     //   53: new 111	entity/Record
/*     */     //   56: dup
/*     */     //   57: invokespecial 174	entity/Record:<init>	()V
/*     */     //   60: astore 9
/*     */     //   62: aload 8
/*     */     //   64: ldc -51
/*     */     //   66: invokeinterface 176 2 0
/*     */     //   71: istore 10
/*     */     //   73: aload 8
/*     */     //   75: ldc -81
/*     */     //   77: invokeinterface 176 2 0
/*     */     //   82: istore 11
/*     */     //   84: aload 8
/*     */     //   86: ldc -76
/*     */     //   88: invokeinterface 181 2 0
/*     */     //   93: astore 12
/*     */     //   95: aload 8
/*     */     //   97: ldc -71
/*     */     //   99: invokeinterface 186 2 0
/*     */     //   104: astore 13
/*     */     //   106: aload 9
/*     */     //   108: iload 11
/*     */     //   110: putfield 110	entity/Record:spend	I
/*     */     //   113: aload 9
/*     */     //   115: iload_1
/*     */     //   116: putfield 121	entity/Record:cid	I
/*     */     //   119: aload 9
/*     */     //   121: aload 12
/*     */     //   123: putfield 124	entity/Record:comment	Ljava/lang/String;
/*     */     //   126: aload 9
/*     */     //   128: aload 13
/*     */     //   130: putfield 131	entity/Record:date	Ljava/util/Date;
/*     */     //   133: aload 9
/*     */     //   135: iload 10
/*     */     //   137: putfield 152	entity/Record:id	I
/*     */     //   140: aload_2
/*     */     //   141: aload 9
/*     */     //   143: invokeinterface 206 2 0
/*     */     //   148: pop
/*     */     //   149: aload 8
/*     */     //   151: invokeinterface 42 1 0
/*     */     //   156: ifne -103 -> 53
/*     */     //   159: aload 7
/*     */     //   161: ifnull +30 -> 191
/*     */     //   164: aload 7
/*     */     //   166: invokeinterface 155 1 0
/*     */     //   171: goto +20 -> 191
/*     */     //   174: astore 4
/*     */     //   176: aload 7
/*     */     //   178: ifnull +10 -> 188
/*     */     //   181: aload 7
/*     */     //   183: invokeinterface 155 1 0
/*     */     //   188: aload 4
/*     */     //   190: athrow
/*     */     //   191: aload 6
/*     */     //   193: ifnull +94 -> 287
/*     */     //   196: aload 6
/*     */     //   198: invokeinterface 75 1 0
/*     */     //   203: goto +84 -> 287
/*     */     //   206: astore 5
/*     */     //   208: aload 4
/*     */     //   210: ifnonnull +10 -> 220
/*     */     //   213: aload 5
/*     */     //   215: astore 4
/*     */     //   217: goto +17 -> 234
/*     */     //   220: aload 4
/*     */     //   222: aload 5
/*     */     //   224: if_acmpeq +10 -> 234
/*     */     //   227: aload 4
/*     */     //   229: aload 5
/*     */     //   231: invokevirtual 76	java/lang/Throwable:addSuppressed	(Ljava/lang/Throwable;)V
/*     */     //   234: aload 6
/*     */     //   236: ifnull +10 -> 246
/*     */     //   239: aload 6
/*     */     //   241: invokeinterface 75 1 0
/*     */     //   246: aload 4
/*     */     //   248: athrow
/*     */     //   249: astore 5
/*     */     //   251: aload 4
/*     */     //   253: ifnonnull +10 -> 263
/*     */     //   256: aload 5
/*     */     //   258: astore 4
/*     */     //   260: goto +17 -> 277
/*     */     //   263: aload 4
/*     */     //   265: aload 5
/*     */     //   267: if_acmpeq +10 -> 277
/*     */     //   270: aload 4
/*     */     //   272: aload 5
/*     */     //   274: invokevirtual 76	java/lang/Throwable:addSuppressed	(Ljava/lang/Throwable;)V
/*     */     //   277: aload 4
/*     */     //   279: athrow
/*     */     //   280: astore 4
/*     */     //   282: aload 4
/*     */     //   284: invokevirtual 82	java/sql/SQLException:printStackTrace	()V
/*     */     //   287: aload_2
/*     */     //   288: areturn
/*     */     // Line number table:
/*     */     //   Java source line #165	-> byte code offset #0
/*     */     //   Java source line #167	-> byte code offset #8
/*     */     //   Java source line #169	-> byte code offset #11
/*     */     //   Java source line #169	-> byte code offset #17
/*     */     //   Java source line #171	-> byte code offset #32
/*     */     //   Java source line #173	-> byte code offset #41
/*     */     //   Java source line #175	-> byte code offset #50
/*     */     //   Java source line #176	-> byte code offset #53
/*     */     //   Java source line #177	-> byte code offset #62
/*     */     //   Java source line #178	-> byte code offset #73
/*     */     //   Java source line #180	-> byte code offset #84
/*     */     //   Java source line #181	-> byte code offset #95
/*     */     //   Java source line #183	-> byte code offset #106
/*     */     //   Java source line #184	-> byte code offset #113
/*     */     //   Java source line #185	-> byte code offset #119
/*     */     //   Java source line #186	-> byte code offset #126
/*     */     //   Java source line #187	-> byte code offset #133
/*     */     //   Java source line #188	-> byte code offset #140
/*     */     //   Java source line #175	-> byte code offset #149
/*     */     //   Java source line #190	-> byte code offset #159
/*     */     //   Java source line #192	-> byte code offset #282
/*     */     //   Java source line #194	-> byte code offset #287
/*     */     // Local variable table:
/*     */     //   start	length	slot	name	signature
/*     */     //   0	289	0	this	RecordDAO
/*     */     //   0	289	1	cid	int
/*     */     //   7	281	2	records	List<Record>
/*     */     //   10	15	3	sql	String
/*     */     //   12	1	4	localObject1	Object
/*     */     //   174	35	4	localObject2	Object
/*     */     //   215	63	4	localObject3	Object
/*     */     //   280	3	4	e	java.sql.SQLException
/*     */     //   15	1	5	localObject4	Object
/*     */     //   206	24	5	localThrowable1	Throwable
/*     */     //   249	24	5	localThrowable2	Throwable
/*     */     //   20	220	6	c	java.sql.Connection
/*     */     //   30	152	7	ps	java.sql.PreparedStatement
/*     */     //   48	102	8	rs	java.sql.ResultSet
/*     */     //   60	82	9	record	Record
/*     */     //   71	65	10	id	int
/*     */     //   82	27	11	spend	int
/*     */     //   93	29	12	comment	String
/*     */     //   104	25	13	date	java.util.Date
/*     */     // Exception table:
/*     */     //   from	to	target	type
/*     */     //   32	159	174	finally
/*     */     //   22	191	206	finally
/*     */     //   17	249	249	finally
/*     */     //   11	280	280	java/sql/SQLException
/*     */   }
/*     */   
/*     */   public List<Record> listToday()
/*     */   {
/* 198 */     return list(DateUtil.today());
/*     */   }
/*     */   
/*     */   /* Error */
/*     */   public List<Record> list(java.util.Date day)
/*     */   {
/*     */     // Byte code:
/*     */     //   0: new 198	java/util/ArrayList
/*     */     //   3: dup
/*     */     //   4: invokespecial 200	java/util/ArrayList:<init>	()V
/*     */     //   7: astore_2
/*     */     //   8: ldc -26
/*     */     //   10: astore_3
/*     */     //   11: aconst_null
/*     */     //   12: astore 4
/*     */     //   14: aconst_null
/*     */     //   15: astore 5
/*     */     //   17: invokestatic 16	util/DBUtil:getConnection	()Ljava/sql/Connection;
/*     */     //   20: astore 6
/*     */     //   22: aload 6
/*     */     //   24: aload_3
/*     */     //   25: invokeinterface 106 2 0
/*     */     //   30: astore 7
/*     */     //   32: aload 7
/*     */     //   34: iconst_1
/*     */     //   35: aload_1
/*     */     //   36: invokestatic 135	util/DateUtil:util2sql	(Ljava/util/Date;)Ljava/sql/Date;
/*     */     //   39: invokeinterface 141 3 0
/*     */     //   44: aload 7
/*     */     //   46: invokeinterface 203 1 0
/*     */     //   51: astore 8
/*     */     //   53: goto +111 -> 164
/*     */     //   56: new 111	entity/Record
/*     */     //   59: dup
/*     */     //   60: invokespecial 174	entity/Record:<init>	()V
/*     */     //   63: astore 9
/*     */     //   65: aload 8
/*     */     //   67: ldc -51
/*     */     //   69: invokeinterface 176 2 0
/*     */     //   74: istore 10
/*     */     //   76: aload 8
/*     */     //   78: ldc -77
/*     */     //   80: invokeinterface 176 2 0
/*     */     //   85: istore 11
/*     */     //   87: aload 8
/*     */     //   89: ldc -81
/*     */     //   91: invokeinterface 176 2 0
/*     */     //   96: istore 12
/*     */     //   98: aload 8
/*     */     //   100: ldc -76
/*     */     //   102: invokeinterface 181 2 0
/*     */     //   107: astore 13
/*     */     //   109: aload 8
/*     */     //   111: ldc -71
/*     */     //   113: invokeinterface 186 2 0
/*     */     //   118: astore 14
/*     */     //   120: aload 9
/*     */     //   122: iload 12
/*     */     //   124: putfield 110	entity/Record:spend	I
/*     */     //   127: aload 9
/*     */     //   129: iload 11
/*     */     //   131: putfield 121	entity/Record:cid	I
/*     */     //   134: aload 9
/*     */     //   136: aload 13
/*     */     //   138: putfield 124	entity/Record:comment	Ljava/lang/String;
/*     */     //   141: aload 9
/*     */     //   143: aload 14
/*     */     //   145: putfield 131	entity/Record:date	Ljava/util/Date;
/*     */     //   148: aload 9
/*     */     //   150: iload 10
/*     */     //   152: putfield 152	entity/Record:id	I
/*     */     //   155: aload_2
/*     */     //   156: aload 9
/*     */     //   158: invokeinterface 206 2 0
/*     */     //   163: pop
/*     */     //   164: aload 8
/*     */     //   166: invokeinterface 42 1 0
/*     */     //   171: ifne -115 -> 56
/*     */     //   174: aload 7
/*     */     //   176: ifnull +30 -> 206
/*     */     //   179: aload 7
/*     */     //   181: invokeinterface 155 1 0
/*     */     //   186: goto +20 -> 206
/*     */     //   189: astore 4
/*     */     //   191: aload 7
/*     */     //   193: ifnull +10 -> 203
/*     */     //   196: aload 7
/*     */     //   198: invokeinterface 155 1 0
/*     */     //   203: aload 4
/*     */     //   205: athrow
/*     */     //   206: aload 6
/*     */     //   208: ifnull +94 -> 302
/*     */     //   211: aload 6
/*     */     //   213: invokeinterface 75 1 0
/*     */     //   218: goto +84 -> 302
/*     */     //   221: astore 5
/*     */     //   223: aload 4
/*     */     //   225: ifnonnull +10 -> 235
/*     */     //   228: aload 5
/*     */     //   230: astore 4
/*     */     //   232: goto +17 -> 249
/*     */     //   235: aload 4
/*     */     //   237: aload 5
/*     */     //   239: if_acmpeq +10 -> 249
/*     */     //   242: aload 4
/*     */     //   244: aload 5
/*     */     //   246: invokevirtual 76	java/lang/Throwable:addSuppressed	(Ljava/lang/Throwable;)V
/*     */     //   249: aload 6
/*     */     //   251: ifnull +10 -> 261
/*     */     //   254: aload 6
/*     */     //   256: invokeinterface 75 1 0
/*     */     //   261: aload 4
/*     */     //   263: athrow
/*     */     //   264: astore 5
/*     */     //   266: aload 4
/*     */     //   268: ifnonnull +10 -> 278
/*     */     //   271: aload 5
/*     */     //   273: astore 4
/*     */     //   275: goto +17 -> 292
/*     */     //   278: aload 4
/*     */     //   280: aload 5
/*     */     //   282: if_acmpeq +10 -> 292
/*     */     //   285: aload 4
/*     */     //   287: aload 5
/*     */     //   289: invokevirtual 76	java/lang/Throwable:addSuppressed	(Ljava/lang/Throwable;)V
/*     */     //   292: aload 4
/*     */     //   294: athrow
/*     */     //   295: astore 4
/*     */     //   297: aload 4
/*     */     //   299: invokevirtual 82	java/sql/SQLException:printStackTrace	()V
/*     */     //   302: aload_2
/*     */     //   303: areturn
/*     */     // Line number table:
/*     */     //   Java source line #202	-> byte code offset #0
/*     */     //   Java source line #203	-> byte code offset #8
/*     */     //   Java source line #204	-> byte code offset #11
/*     */     //   Java source line #204	-> byte code offset #17
/*     */     //   Java source line #205	-> byte code offset #32
/*     */     //   Java source line #207	-> byte code offset #44
/*     */     //   Java source line #208	-> byte code offset #53
/*     */     //   Java source line #209	-> byte code offset #56
/*     */     //   Java source line #210	-> byte code offset #65
/*     */     //   Java source line #211	-> byte code offset #76
/*     */     //   Java source line #212	-> byte code offset #87
/*     */     //   Java source line #214	-> byte code offset #98
/*     */     //   Java source line #215	-> byte code offset #109
/*     */     //   Java source line #217	-> byte code offset #120
/*     */     //   Java source line #218	-> byte code offset #127
/*     */     //   Java source line #219	-> byte code offset #134
/*     */     //   Java source line #220	-> byte code offset #141
/*     */     //   Java source line #221	-> byte code offset #148
/*     */     //   Java source line #222	-> byte code offset #155
/*     */     //   Java source line #208	-> byte code offset #164
/*     */     //   Java source line #224	-> byte code offset #174
/*     */     //   Java source line #226	-> byte code offset #297
/*     */     //   Java source line #228	-> byte code offset #302
/*     */     // Local variable table:
/*     */     //   start	length	slot	name	signature
/*     */     //   0	304	0	this	RecordDAO
/*     */     //   0	304	1	day	java.util.Date
/*     */     //   7	296	2	records	List<Record>
/*     */     //   10	15	3	sql	String
/*     */     //   12	1	4	localObject1	Object
/*     */     //   189	35	4	localObject2	Object
/*     */     //   230	63	4	localObject3	Object
/*     */     //   295	3	4	e	java.sql.SQLException
/*     */     //   15	1	5	localObject4	Object
/*     */     //   221	24	5	localThrowable1	Throwable
/*     */     //   264	24	5	localThrowable2	Throwable
/*     */     //   20	235	6	c	java.sql.Connection
/*     */     //   30	167	7	ps	java.sql.PreparedStatement
/*     */     //   51	114	8	rs	java.sql.ResultSet
/*     */     //   63	94	9	record	Record
/*     */     //   74	77	10	id	int
/*     */     //   85	45	11	cid	int
/*     */     //   96	27	12	spend	int
/*     */     //   107	30	13	comment	String
/*     */     //   118	26	14	date	java.util.Date
/*     */     // Exception table:
/*     */     //   from	to	target	type
/*     */     //   32	174	189	finally
/*     */     //   22	206	221	finally
/*     */     //   17	264	264	finally
/*     */     //   11	295	295	java/sql/SQLException
/*     */   }
/*     */   
/*     */   public List<Record> listThisMonth()
/*     */   {
/* 232 */     return list(DateUtil.monthBegin(), DateUtil.monthEnd());
/*     */   }
/*     */   
/*     */   /* Error */
/*     */   public List<Record> list(java.util.Date start, java.util.Date end)
/*     */   {
/*     */     // Byte code:
/*     */     //   0: new 198	java/util/ArrayList
/*     */     //   3: dup
/*     */     //   4: invokespecial 200	java/util/ArrayList:<init>	()V
/*     */     //   7: astore_3
/*     */     //   8: ldc -10
/*     */     //   10: astore 4
/*     */     //   12: aconst_null
/*     */     //   13: astore 5
/*     */     //   15: aconst_null
/*     */     //   16: astore 6
/*     */     //   18: invokestatic 16	util/DBUtil:getConnection	()Ljava/sql/Connection;
/*     */     //   21: astore 7
/*     */     //   23: aload 7
/*     */     //   25: aload 4
/*     */     //   27: invokeinterface 106 2 0
/*     */     //   32: astore 8
/*     */     //   34: aload 8
/*     */     //   36: iconst_1
/*     */     //   37: aload_1
/*     */     //   38: invokestatic 135	util/DateUtil:util2sql	(Ljava/util/Date;)Ljava/sql/Date;
/*     */     //   41: invokeinterface 141 3 0
/*     */     //   46: aload 8
/*     */     //   48: iconst_2
/*     */     //   49: aload_2
/*     */     //   50: invokestatic 135	util/DateUtil:util2sql	(Ljava/util/Date;)Ljava/sql/Date;
/*     */     //   53: invokeinterface 141 3 0
/*     */     //   58: aload 8
/*     */     //   60: invokeinterface 203 1 0
/*     */     //   65: astore 9
/*     */     //   67: goto +111 -> 178
/*     */     //   70: new 111	entity/Record
/*     */     //   73: dup
/*     */     //   74: invokespecial 174	entity/Record:<init>	()V
/*     */     //   77: astore 10
/*     */     //   79: aload 9
/*     */     //   81: ldc -51
/*     */     //   83: invokeinterface 176 2 0
/*     */     //   88: istore 11
/*     */     //   90: aload 9
/*     */     //   92: ldc -77
/*     */     //   94: invokeinterface 176 2 0
/*     */     //   99: istore 12
/*     */     //   101: aload 9
/*     */     //   103: ldc -81
/*     */     //   105: invokeinterface 176 2 0
/*     */     //   110: istore 13
/*     */     //   112: aload 9
/*     */     //   114: ldc -76
/*     */     //   116: invokeinterface 181 2 0
/*     */     //   121: astore 14
/*     */     //   123: aload 9
/*     */     //   125: ldc -71
/*     */     //   127: invokeinterface 186 2 0
/*     */     //   132: astore 15
/*     */     //   134: aload 10
/*     */     //   136: iload 13
/*     */     //   138: putfield 110	entity/Record:spend	I
/*     */     //   141: aload 10
/*     */     //   143: iload 12
/*     */     //   145: putfield 121	entity/Record:cid	I
/*     */     //   148: aload 10
/*     */     //   150: aload 14
/*     */     //   152: putfield 124	entity/Record:comment	Ljava/lang/String;
/*     */     //   155: aload 10
/*     */     //   157: aload 15
/*     */     //   159: putfield 131	entity/Record:date	Ljava/util/Date;
/*     */     //   162: aload 10
/*     */     //   164: iload 11
/*     */     //   166: putfield 152	entity/Record:id	I
/*     */     //   169: aload_3
/*     */     //   170: aload 10
/*     */     //   172: invokeinterface 206 2 0
/*     */     //   177: pop
/*     */     //   178: aload 9
/*     */     //   180: invokeinterface 42 1 0
/*     */     //   185: ifne -115 -> 70
/*     */     //   188: aload 8
/*     */     //   190: ifnull +30 -> 220
/*     */     //   193: aload 8
/*     */     //   195: invokeinterface 155 1 0
/*     */     //   200: goto +20 -> 220
/*     */     //   203: astore 5
/*     */     //   205: aload 8
/*     */     //   207: ifnull +10 -> 217
/*     */     //   210: aload 8
/*     */     //   212: invokeinterface 155 1 0
/*     */     //   217: aload 5
/*     */     //   219: athrow
/*     */     //   220: aload 7
/*     */     //   222: ifnull +94 -> 316
/*     */     //   225: aload 7
/*     */     //   227: invokeinterface 75 1 0
/*     */     //   232: goto +84 -> 316
/*     */     //   235: astore 6
/*     */     //   237: aload 5
/*     */     //   239: ifnonnull +10 -> 249
/*     */     //   242: aload 6
/*     */     //   244: astore 5
/*     */     //   246: goto +17 -> 263
/*     */     //   249: aload 5
/*     */     //   251: aload 6
/*     */     //   253: if_acmpeq +10 -> 263
/*     */     //   256: aload 5
/*     */     //   258: aload 6
/*     */     //   260: invokevirtual 76	java/lang/Throwable:addSuppressed	(Ljava/lang/Throwable;)V
/*     */     //   263: aload 7
/*     */     //   265: ifnull +10 -> 275
/*     */     //   268: aload 7
/*     */     //   270: invokeinterface 75 1 0
/*     */     //   275: aload 5
/*     */     //   277: athrow
/*     */     //   278: astore 6
/*     */     //   280: aload 5
/*     */     //   282: ifnonnull +10 -> 292
/*     */     //   285: aload 6
/*     */     //   287: astore 5
/*     */     //   289: goto +17 -> 306
/*     */     //   292: aload 5
/*     */     //   294: aload 6
/*     */     //   296: if_acmpeq +10 -> 306
/*     */     //   299: aload 5
/*     */     //   301: aload 6
/*     */     //   303: invokevirtual 76	java/lang/Throwable:addSuppressed	(Ljava/lang/Throwable;)V
/*     */     //   306: aload 5
/*     */     //   308: athrow
/*     */     //   309: astore 5
/*     */     //   311: aload 5
/*     */     //   313: invokevirtual 82	java/sql/SQLException:printStackTrace	()V
/*     */     //   316: aload_3
/*     */     //   317: areturn
/*     */     // Line number table:
/*     */     //   Java source line #236	-> byte code offset #0
/*     */     //   Java source line #237	-> byte code offset #8
/*     */     //   Java source line #238	-> byte code offset #12
/*     */     //   Java source line #238	-> byte code offset #18
/*     */     //   Java source line #239	-> byte code offset #34
/*     */     //   Java source line #240	-> byte code offset #46
/*     */     //   Java source line #241	-> byte code offset #58
/*     */     //   Java source line #242	-> byte code offset #67
/*     */     //   Java source line #243	-> byte code offset #70
/*     */     //   Java source line #244	-> byte code offset #79
/*     */     //   Java source line #245	-> byte code offset #90
/*     */     //   Java source line #246	-> byte code offset #101
/*     */     //   Java source line #248	-> byte code offset #112
/*     */     //   Java source line #249	-> byte code offset #123
/*     */     //   Java source line #251	-> byte code offset #134
/*     */     //   Java source line #252	-> byte code offset #141
/*     */     //   Java source line #253	-> byte code offset #148
/*     */     //   Java source line #254	-> byte code offset #155
/*     */     //   Java source line #255	-> byte code offset #162
/*     */     //   Java source line #256	-> byte code offset #169
/*     */     //   Java source line #242	-> byte code offset #178
/*     */     //   Java source line #258	-> byte code offset #188
/*     */     //   Java source line #260	-> byte code offset #311
/*     */     //   Java source line #262	-> byte code offset #316
/*     */     // Local variable table:
/*     */     //   start	length	slot	name	signature
/*     */     //   0	318	0	this	RecordDAO
/*     */     //   0	318	1	start	java.util.Date
/*     */     //   0	318	2	end	java.util.Date
/*     */     //   7	310	3	records	List<Record>
/*     */     //   10	16	4	sql	String
/*     */     //   13	1	5	localObject1	Object
/*     */     //   203	35	5	localObject2	Object
/*     */     //   244	63	5	localObject3	Object
/*     */     //   309	3	5	e	java.sql.SQLException
/*     */     //   16	1	6	localObject4	Object
/*     */     //   235	24	6	localThrowable1	Throwable
/*     */     //   278	24	6	localThrowable2	Throwable
/*     */     //   21	248	7	c	java.sql.Connection
/*     */     //   32	179	8	ps	java.sql.PreparedStatement
/*     */     //   65	114	9	rs	java.sql.ResultSet
/*     */     //   77	94	10	record	Record
/*     */     //   88	77	11	id	int
/*     */     //   99	45	12	cid	int
/*     */     //   110	27	13	spend	int
/*     */     //   121	30	14	comment	String
/*     */     //   132	26	15	date	java.util.Date
/*     */     // Exception table:
/*     */     //   from	to	target	type
/*     */     //   34	188	203	finally
/*     */     //   23	220	235	finally
/*     */     //   18	278	278	finally
/*     */     //   12	309	309	java/sql/SQLException
/*     */   }
/*     */ }


/* Location:              E:\java\java\hutubill\lib\all.jar!\dao\RecordDAO.class
 * Java compiler version: 8 (52.0)
 * JD-Core Version:       0.7.1
 */